openvino_tokenizers/__init__.py
openvino_tokenizers/__version__.py
openvino_tokenizers/build_tokenizer.py
openvino_tokenizers/cli.py
openvino_tokenizers/constants.py
openvino_tokenizers/convert_tokenizer.py
openvino_tokenizers/hf_parser.py
openvino_tokenizers/tiktoken_parser.py
openvino_tokenizers/tokenizer_pipeline.py
openvino_tokenizers/tokenizer_transformations.py
openvino_tokenizers/utils.py
openvino_tokenizers/lib/libopenvino_tokenizers.so
openvino_tokenizers-2025.3.0.0.dist-info/LICENSE
openvino_tokenizers-2025.3.0.0.dist-info/METADATA
openvino_tokenizers-2025.3.0.0.dist-info/SECURITY.md
openvino_tokenizers-2025.3.0.0.dist-info/WHEEL
openvino_tokenizers-2025.3.0.0.dist-info/entry_points.txt
openvino_tokenizers-2025.3.0.0.dist-info/third-party-programs.txt
openvino_tokenizers-2025.3.0.0.dist-info/RECORD
