Metadata-Version: 2.1
Name: openvino-tokenizers
Version: 2025.3.0.0
Summary: Convert tokenizers into OpenVINO models
Author-Email: OpenVINO Developers <openvino@intel.com>
License: Apache-2.0
Classifier: Development Status :: 5 - Production/Stable
Classifier: License :: OSI Approved :: Apache Software License
Classifier: Intended Audience :: Developers
Classifier: Intended Audience :: Science/Research
Classifier: Topic :: Scientific/Engineering :: Artificial Intelligence
Classifier: Topic :: Software Development :: Libraries :: Python Modules
Classifier: Programming Language :: Python :: 3.9
Classifier: Programming Language :: Python :: 3.10
Classifier: Programming Language :: Python :: 3.11
Classifier: Programming Language :: Python :: 3.12
Classifier: Programming Language :: Python :: 3.13
Classifier: Operating System :: Unix
Classifier: Operating System :: POSIX :: Linux
Classifier: Operating System :: Microsoft :: Windows
Classifier: Operating System :: MacOS
Classifier: Programming Language :: C++
Classifier: Programming Language :: C
Classifier: Programming Language :: Python :: 3 :: Only
Requires-Python: >=3.9
Requires-Dist: openvino~=2025.3.0.dev
Requires-Dist: transformers[sentencepiece]>=4.36.0; extra == "transformers"
Requires-Dist: tiktoken>=0.3.0; extra == "transformers"
Provides-Extra: transformers
